{
  "version": "2.0.0",
  "licenses": {
    "ignoreList": [
      "@kaltura-ng/kaltura-common",
      "@kaltura-ng/kaltura-primeng-ui",
      "@kaltura-ng/kaltura-ui",
      "@kaltura-ng/mc-theme",
      "@kaltura-ng/dev-workspace"
    ]
  },
  "commands": {
    "bookmark": {
      "standalone": [
        "ab6e7441af13ab94d2661da59b1ea396206ee72d"
      ]
    },
    "release": {
      "appConfig": {
        "path": "./src/configuration/global-config.ts",
        "key": "appVersion"
      },
      "changeLog": {
        "htmlPath": ""
      }
    }
  }
}
